{"code":"005940","name":"NH투자증권","updatedAt":"2026-07-24T15:30:30+09:00","price":29000,"change":-1000,"changeRate":-3.33,"buy":61,"sell":28,"grade":"gold","scores":{"fin":{"total":76,"parts":{"profitability":{"score":65,"label":"수익성","explain":"자본과 매출을 이익으로 바꾸는 효율을 ROE와 영업이익률로 측정합니다. 2025.12 확정 기준 ROE 11.8%, 영업이익률 10.4%. ROE 코스피200 상위 31% · 영업이익률 상위 30% → 수익성 65점","inputs":[{"label":"ROE(2025.12)","value":"11.8%"},{"label":"영업이익률","value":"10.4%"}],"reasons":["ROE 코스피200 상위 31%","영업이익률 상위 30%"]},"growth":{"score":79,"label":"성장성","explain":"매출과 영업이익이 얼마나 빠르게 늘고 있는지를 최근 1년과 2년 추세로 함께 봅니다. 2025.12 매출 YoY +36.5%, 영업이익 YoY +57.7%, 2년 연평균 매출 +14.9%. 영업이익 성장 코스피200 상위 23% 수준 → 성장성 79점","inputs":[{"label":"매출 YoY","value":"+36.5%"},{"label":"영업이익 YoY","value":"+57.7%"},{"label":"2년 매출 CAGR","value":"+14.9%"},{"label":"2년 영업이익 CAGR","value":"+39.9%"}],"reasons":[]},"stability":{"score":87,"label":"안정성","explain":"부채 부담과 배당 여력으로 재무 하방 안정성을 측정합니다. 금융업 특성상 부채비율은 평가에서 제외했습니다. 배당수익률 4.5%. 배당 상위 10% → 안정성 87점","inputs":[{"label":"배당수익률","value":"4.5%"}],"reasons":["금융업 특성상 부채비율 평가 제외"]},"risk":{"score":0,"label":"재무 리스크","explain":"재무제표에서 확인되는 위험 신호(적자, 과다 부채, 매출 급감)를 누적 가산합니다. 확인된 재무 위험 신호가 없습니다 (0점).","inputs":[],"reasons":[]}},"reasons":["ROE 11.8%로 코스피200 상위 31%","2025.12 영업이익 전년 대비 +57.7%","금융업 특성상 부채비율 평가 제외"]},"out":{"total":80,"parts":{"revenueGrowth":{"score":92,"label":"매출 성장 전망","explain":"애널리스트들이 전망하는 2026.12 매출액이 최근 확정 실적 대비 얼마나 늘어나는지를 봅니다. 2025.12 136,989억원 → 2026.12 컨센서스 238,824억원 (+74.3%). 전망 성장률 코스피200 상위 3% → 92점","inputs":[{"label":"매출액(2025.12)","value":"136,989억원"},{"label":"컨센서스(2026.12)","value":"238,824억원"},{"label":"전망 성장률","value":"+74.3%"}],"reasons":[]},"opGrowth":{"score":74,"label":"영업이익 성장 전망","explain":"애널리스트들이 전망하는 2026.12 영업이익이 최근 확정 실적 대비 얼마나 늘어나는지를 봅니다. 2025.12 14,206억원 → 2026.12 컨센서스 22,124억원 (+55.7%). 전망 성장률 코스피200 상위 36% → 74점","inputs":[{"label":"영업이익(2025.12)","value":"14,206억원"},{"label":"컨센서스(2026.12)","value":"22,124억원"},{"label":"전망 성장률","value":"+55.7%"}],"reasons":[]},"epsGrowth":{"score":69,"label":"EPS 성장 전망","explain":"애널리스트들이 전망하는 2026.12 EPS이 최근 확정 실적 대비 얼마나 늘어나는지를 봅니다. 2025.12 2,888원 → 2026.12 컨센서스 4,430원 (+53.4%). 전망 성장률 코스피200 상위 44% → 69점","inputs":[{"label":"EPS(2025.12)","value":"2,888원"},{"label":"컨센서스(2026.12)","value":"4,430원"},{"label":"전망 성장률","value":"+53.4%"}],"reasons":[]},"targetUpside":{"score":89,"label":"목표주가","explain":"애널리스트 평균 목표주가가 현재 주가보다 얼마나 높은지(괴리율)를 봅니다. 평균 목표주가 42,750원 vs 현재가 29,000원 → 괴리율 47.4%. 괴리율 47.4%는 통상적 상방 편향(+15% 내외)을 크게 상회 → 89점 (참고: 투자의견 평균 3.94/5)","inputs":[{"label":"평균 목표주가","value":"42,750원"},{"label":"현재가","value":"29,000원"},{"label":"괴리율","value":"+47.4%"},{"label":"투자의견 평균","value":"3.94/5"}],"reasons":["목표주가 괴리율이 상방 편향을 크게 상회"]},"valuation":{"score":77,"label":"밸류에이션","explain":"이익·자산 대비 주가 수준(PER·PBR)이 싼지 비싼지를 절대 구간과 지수 내 상대 위치로 함께 봅니다. 금융업은 구조적 저PBR 특성을 감안해 PER 중심으로 평가합니다. 추정PER 6.6배(전망 이익 기준), PBR 1.1배. PER 절대 구간 저평가 · 지수 내 상위 14% → 77점","inputs":[{"label":"추정PER","value":"6.6배"},{"label":"PBR","value":"1.1배"}],"reasons":["PER 6.6배로 지수 하위 14% 저평가"]},"risk":{"score":0,"label":"전망 리스크","explain":"전망 측면의 위험 신호(이익 감소 전망, 목표주가 하회, 성장 없는 고평가)를 누적 가산합니다. 확인된 전망 위험 신호가 없습니다 (0점).","inputs":[],"reasons":[]}},"reasons":["2026.12 컨센서스 영업이익 +55.7% 전망","평균 목표주가 대비 상승여력 47.4%","2026.12 컨센서스 매출액 +74.3% 전망","추정PER 6.6배로 지수 하위 14% 저평가"],"hasConsensus":true},"tech":{"buy":30,"sell":50,"parts":{"rsi":{"score":43,"label":"RSI","explain":"최근 14일 상승/하락 강도로 과매수·과매도를 측정하되, 추세 방향에 따라 해석을 달리합니다. RSI(14) 44.6 / 추세 상태: 하락추세. 중립권 → 43점","inputs":[{"label":"RSI(14)","value":44.6},{"label":"추세 상태","value":"하락추세"}],"reasons":[]},"macd":{"score":12,"label":"MACD","explain":"단기(12일)·장기(26일) 이동평균 차이로 모멘텀의 방향 전환을 포착합니다. MACD -394.82 / 시그널 -304.31 / 히스토그램 -90.5 (축소) / 상태: 데드크로스. 데드크로스 + 히스토그램 축소 → 12점","inputs":[{"label":"MACD","value":-394.82},{"label":"시그널","value":-304.31},{"label":"히스토그램","value":-90.5},{"label":"상태","value":"데드크로스"}],"reasons":["MACD 시그널 하향 이탈(데드크로스)"]},"trend":{"score":25,"label":"추세","explain":"주가가 20일·60일 이동평균 위에 있는지, 최근 20일 상승 폭과 52주 내 위치로 추세 건강도를 봅니다. 종가 29,000 vs MA20 30,148 / MA60 31,699, 20일 모멘텀 -0.3%, 52주 위치 41 (0=최저가, 100=최고가). MA20/60 하회 · 모멘텀 -0.3%, 52주 중간권 → 25점","inputs":[{"label":"종가","value":"29,000"},{"label":"MA20","value":"30,148"},{"label":"MA60","value":"31,699"},{"label":"20일 모멘텀","value":"-0.3%"},{"label":"52주 위치","value":41}],"reasons":["MA20/60 하회","52주 중간권"]},"band":{"score":45,"label":"볼린저밴드","explain":"20일 평균 대비 주가가 통계적 밴드(±2σ)의 어디에 있는지로 단기 과열·눌림을 측정합니다. %b 0.28 (0=하단 밴드, 1=상단 밴드), MA20 이격도 -3.8%. %b 밴드 중간 → 45점","inputs":[{"label":"%b(20,2)","value":0.28},{"label":"MA20 이격도","value":"-3.8%"}],"reasons":[]},"volume":{"score":null,"label":"거래량·수급","explain":"거래대금이 최근 20일 평균 대비 통계적으로 얼마나 튀었는지(Z-score)와 투자자별(외국인·기관·개인) 5일 순매수 방향을 봅니다. 거래대금 Z -0.8 (2 이상이면 급증), 외인+기관 5일 순매수/거래량 0.3% (개인 -0.32%). 특이 신호 없음 → 가감 없음","inputs":[{"label":"거래대금 Z(20)","value":-0.8},{"label":"외국인 5일 순매수/거래량","value":"0.89%"},{"label":"기관 5일 순매수/거래량","value":"-0.59%"},{"label":"개인 5일 순매수/거래량","value":"-0.32%"},{"label":"외인+기관 5일 순매수/거래량","value":"0.3%"}],"reasons":[],"buyScore":0,"sellScore":0},"sellSignals":{"score":50,"label":"매도 신호","explain":"과열·추세이탈·투매 등 \"지금 팔 이유\"가 되는 이벤트를 하나씩 가산합니다(기본 15점). 발동 신호: 데드크로스(+15), 종가 MA20·MA60 동시 하회(+12), MA20 < MA60 역배열(+8). 매도 신호 3건 → TECH_sell 50점","inputs":[{"label":"데드크로스","value":"+15점"},{"label":"종가 MA20·MA60 동시 하회","value":"+12점"},{"label":"MA20 < MA60 역배열","value":"+8점"}],"reasons":["데드크로스(+15)","종가 MA20·MA60 동시 하회(+12)","MA20 < MA60 역배열(+8)"],"sellScore":50}},"reasons":["MACD 시그널 하향 이탈(데드크로스)","RSI 44.6 중립권","종가가 MA20/MA60 모두 하회(하락 배열)"]}},"indicators":{"rsi":44.6,"macd":-394.82,"signal":-304.31,"hist":-90.5,"ma20":30147.5,"ma60":31699.2,"momentum20d":-0.3,"bollingerB":0.28,"pos52w":41,"volumeZ":-0.8,"disparity20":-3.8,"atrPct":6.6,"flowRatio":0.003,"flow":{"foreign5":24930,"organ5":-16444,"indiv5":-9070,"foreignRatio":0.0089,"organRatio":-0.0059,"indivRatio":-0.0032},"foreignRate":13.18,"trendState":"down"},"targetPrice":{"value":42550,"upside":46.7,"method":"blend","components":{"analyst":{"raw":42750,"discounted":40613},"valuation":{"epsFwd":4430,"perNow":6.55,"perMkt":11.47,"perTarget":8.67,"growthAdj":1.15,"value":44145}},"capped":false,"capNote":null,"explain":["추정 EPS 4,430원 × 목표 PER 8.67배(현재 PER 6.55배와 시장 중앙값 11.47배의 기하평균, −15%~+35% 밴드 제한) × 성장 조정 1.15(컨센서스 영업이익 성장 +30%의 50% 반영) = 44,145원.","애널리스트 평균 목표주가 42,750원에 국내 상방 편향 할인 5%를 적용해 40,613원으로 반영했습니다.","두 성분을 애널리스트 45% : 밸류에이션 55%로 가중 평균했습니다.","KRX 호가단위 반올림 후 목표주가 42,550원 — 현재가 대비 상승여력 +46.7%입니다."]},"verdict":{"stance":"중립","text":"코스피200 상대평가 골드 등급으로 매수 매력도(BUY) 61점, 매도 신호(SELL) 28점입니다. 가장 강한 항목은 매출 성장 전망(92점)이고, 상대적 약점은 MACD(12점)입니다. 기술적으로는 하락추세 국면에 RSI 44.6(중립권)입니다. 목표주가 42,550원 기준 상승여력은 +46.7%입니다."},"financials":{"years":["2023.12","2024.12","2025.12","2026.12(E)"],"revenue":[103712,100342,136989,238824],"op":[7258,9011,14206,22124],"netIncome":[5530,6866,10315,16518],"roe":[7.5,8.73,11.76,16.82],"debtRatio":[644.71,668.87,783.5,null],"per":[6.51,7.06,7.31,6.77],"pbr":[0.47,0.59,0.84,1.09],"eps":[1587,1976,2888,4430]},"chart":{"dates":["2026-01-27","2026-01-28","2026-01-29","2026-01-30","2026-02-02","2026-02-03","2026-02-04","2026-02-05","2026-02-06","2026-02-09","2026-02-10","2026-02-11","2026-02-12","2026-02-13","2026-02-19","2026-02-20","2026-02-23","2026-02-24","2026-02-25","2026-02-26","2026-02-27","2026-03-03","2026-03-04","2026-03-05","2026-03-06","2026-03-09","2026-03-10","2026-03-11","2026-03-12","2026-03-13","2026-03-16","2026-03-17","2026-03-18","2026-03-19","2026-03-20","2026-03-23","2026-03-24","2026-03-25","2026-03-26","2026-03-27","2026-03-30","2026-03-31","2026-04-01","2026-04-02","2026-04-03","2026-04-06","2026-04-07","2026-04-08","2026-04-09","2026-04-10","2026-04-13","2026-04-14","2026-04-15","2026-04-16","2026-04-17","2026-04-20","2026-04-21","2026-04-22","2026-04-23","2026-04-24","2026-04-27","2026-04-28","2026-04-29","2026-04-30","2026-05-04","2026-05-06","2026-05-07","2026-05-08","2026-05-11","2026-05-12","2026-05-13","2026-05-14","2026-05-15","2026-05-18","2026-05-19","2026-05-20","2026-05-21","2026-05-22","2026-05-26","2026-05-27","2026-05-28","2026-05-29","2026-06-01","2026-06-02","2026-06-04","2026-06-05","2026-06-08","2026-06-09","2026-06-10","2026-06-11","2026-06-12","2026-06-15","2026-06-16","2026-06-17","2026-06-18","2026-06-19","2026-06-22","2026-06-23","2026-06-24","2026-06-25","2026-06-26","2026-06-29","2026-06-30","2026-07-01","2026-07-02","2026-07-03","2026-07-06","2026-07-07","2026-07-08","2026-07-09","2026-07-10","2026-07-13","2026-07-14","2026-07-15","2026-07-16","2026-07-20","2026-07-21","2026-07-22","2026-07-23","2026-07-24"],"close":[24600,24900,26050,27050,25150,27050,27100,26300,25950,26750,28450,29000,29150,30900,36750,39200,38350,36400,36400,36500,35500,33300,28800,32050,32200,30550,31400,33300,32550,31700,31750,32400,34200,33400,35600,32700,32950,34300,33250,34250,30950,29600,31850,29750,29950,30450,30550,33850,33500,34050,33850,35200,35350,35200,35300,35150,35950,35600,34950,35100,35250,35050,34600,33650,36450,38450,37700,36600,36050,34000,33550,35000,32550,31950,31050,30450,31900,32850,32000,31150,30450,30200,31200,30650,31600,31750,29450,31250,30500,31200,31750,32700,32850,32350,31450,32000,30800,28750,28750,29100,27700,29150,29400,29550,28950,31400,33100,31850,30650,29250,31600,31150,29800,31100,31000,29500,29750,29050,30000,29000],"volume":[811427,982547,1497255,1696981,1170374,1164308,1206584,948626,868253,1025337,1580715,1216479,1343089,2701427,3112595,4574149,2667473,2698783,1570132,1760825,1954697,1631800,1927329,1355564,953775,914249,872581,1398587,1315355,1038286,1079730,549879,976125,673415,1466630,1125405,832878,977000,752020,1078231,1647274,1540647,898244,1192519,535635,833235,741570,1327868,1080617,801798,628538,874254,887492,667825,623866,581857,630615,742740,982908,823905,772342,707755,613100,621876,2397495,2702291,1266709,808582,803713,1460073,831713,1120580,1051237,859796,1211427,1136595,1121477,897674,1045049,1184663,1043950,2206720,1063664,1299899,1068223,1730975,1357408,790675,776054,1522922,1068844,1038661,994947,715124,642522,1202341,889700,727684,576249,572182,833603,695336,639631,532295,556109,957186,1108412,831109,679087,770807,899330,1155645,922752,1108916,437936,552776,610350,712545,489861,585030],"rsi14":[72.7,74.2,78.8,81.9,63.2,70.5,70.6,64.5,61.9,65.3,71.1,72.7,73.2,77.7,86.1,88.1,83.6,74.1,74.1,74.3,69.3,59.9,46,54.2,54.6,50.1,52.3,56.8,54.6,52.1,52.3,54.1,58.8,56.1,61.4,52.4,53,56.4,53.2,55.8,46.6,43.4,49.6,44.7,45.2,46.7,47,55.8,54.7,56.1,55.5,59,59.4,58.8,59.1,58.4,61,59.2,56.1,56.7,57.3,56.1,53.6,48.6,60.3,66.3,62.5,57.3,54.9,46.9,45.3,51,42.9,41.2,38.7,37.1,43.3,46.9,44.2,41.5,39.5,38.7,43.3,41.5,45.8,46.5,38.6,46.3,43.8,46.7,48.8,52.5,53.1,50.9,47.1,49.6,44.7,37.9,37.9,39.7,35.2,42.4,43.6,44.3,42,52.9,58.7,53.5,49,44.3,52.5,51,46.5,51,50.6,45.6,46.5,44.2,48,44.6],"macd":[734.83,837.59,1000.29,1196.14,1184.38,1313.24,1403.22,1393.91,1342.81,1351.29,1478.14,1604.56,1697.29,1890.2,2486.46,3120.72,3514.29,3627.03,3674.02,3676.95,3557.57,3248,2609.47,2338.72,2111.9,1778.51,1564.84,1531.17,1427.51,1262.22,1122.33,1051.79,1128.12,1111.26,1260.88,1132.39,1038.77,1061.27,983.04,990.32,721.49,394.96,314.11,79.67,-88.96,-180.18,-241.62,-23.76,119.29,273.87,375.91,559.27,708.51,805.4,880.11,916.65,998.65,1023.59,979.61,945.96,920.78,874.61,792.57,643.48,742.69,971.51,1079.88,1064.73,996.85,768.78,545.43,479.9,227.64,-20.45,-286.39,-539.34,-615.71,-592.74,-635.8,-730.1,-851.49,-956.84,-948.71,-975.4,-909.41,-835.38,-951.33,-887.75,-887.65,-821.61,-716.63,-550.44,-401.99,-320.98,-325.66,-281.73,-339.84,-545.02,-699.56,-784.75,-954.23,-960.47,-934.48,-891.49,-895.52,-693.02,-390.87,-249.39,-231.44,-326.41,-209.64,-151.66,-212.2,-153.5,-113.75,-200.96,-247.06,-336.2,-326.42,-394.82],"signal":[462.07,537.17,629.8,743.07,831.33,927.71,1022.81,1097.03,1146.19,1187.21,1245.39,1317.23,1393.24,1492.63,1691.4,1977.26,2284.67,2553.14,2777.32,2957.24,3077.31,3111.45,3011.05,2876.58,2723.65,2534.62,2340.66,2178.76,2028.51,1875.26,1724.67,1590.09,1497.7,1420.41,1388.5,1337.28,1277.58,1234.32,1184.06,1145.31,1060.55,927.43,804.77,659.75,510.01,371.97,249.25,194.65,179.58,198.44,233.93,299,380.9,465.8,548.66,622.26,697.54,762.75,806.12,834.09,851.43,856.06,843.37,803.39,791.25,827.3,877.82,915.2,931.53,898.98,828.27,758.59,652.4,517.83,356.99,177.72,19.04,-103.32,-209.82,-313.87,-421.4,-528.49,-612.53,-685.1,-729.96,-751.05,-791.1,-810.43,-825.88,-825.02,-803.34,-752.76,-682.61,-610.28,-553.36,-499.03,-467.19,-482.76,-526.12,-577.85,-653.12,-714.59,-758.57,-785.15,-807.23,-784.39,-705.68,-614.42,-537.83,-495.54,-438.36,-381.02,-347.26,-308.51,-269.55,-255.84,-254.08,-270.5,-281.69,-304.31]}}