{"code":"021240","name":"코웨이","updatedAt":"2026-07-24T16:57:09+09:00","price":91800,"change":1100,"changeRate":1.21,"buy":60,"sell":11,"grade":"silver","scores":{"fin":{"total":70,"parts":{"profitability":{"score":85,"label":"수익성","explain":"자본과 매출을 이익으로 바꾸는 효율을 ROE와 영업이익률로 측정합니다. 2025.12 확정 기준 ROE 18.1%, 영업이익률 17.7%. ROE 코스피200 상위 16% · 영업이익률 상위 12% → 수익성 85점","inputs":[{"label":"ROE(2025.12)","value":"18.1%"},{"label":"영업이익률","value":"17.7%"}],"reasons":["ROE 코스피200 상위 16%","영업이익률 상위 12%"]},"growth":{"score":61,"label":"성장성","explain":"매출과 영업이익이 얼마나 빠르게 늘고 있는지를 최근 1년과 2년 추세로 함께 봅니다. 2025.12 매출 YoY +15.2%, 영업이익 YoY +10.5%, 2년 연평균 매출 +11.9%. 영업이익 성장 코스피200 상위 45% 수준 → 성장성 61점","inputs":[{"label":"매출 YoY","value":"+15.2%"},{"label":"영업이익 YoY","value":"+10.5%"},{"label":"2년 매출 CAGR","value":"+11.9%"},{"label":"2년 영업이익 CAGR","value":"+9.6%"}],"reasons":[]},"stability":{"score":59,"label":"안정성","explain":"부채 부담과 배당 여력으로 재무 하방 안정성을 측정합니다. 부채비율 93.7% (2025.12), 배당수익률 2.1%. 부채비율 안정적 · 배당 상위 48% → 안정성 59점","inputs":[{"label":"부채비율(2025.12)","value":"93.7%"},{"label":"배당수익률","value":"2.1%"}],"reasons":["부채비율 93.7%로 안정적"]},"risk":{"score":0,"label":"재무 리스크","explain":"재무제표에서 확인되는 위험 신호(적자, 과다 부채, 매출 급감)를 누적 가산합니다. 확인된 재무 위험 신호가 없습니다 (0점).","inputs":[],"reasons":[]}},"reasons":["ROE 18.1%로 코스피200 상위 16%","2025.12 영업이익 전년 대비 +10.5%","부채비율 93.7%로 재무구조 안정적"]},"out":{"total":59,"parts":{"revenueGrowth":{"score":59,"label":"매출 성장 전망","explain":"애널리스트들이 전망하는 2026.12 매출액이 최근 확정 실적 대비 얼마나 늘어나는지를 봅니다. 2025.12 49,636억원 → 2026.12 컨센서스 56,250억원 (+13.3%). 전망 성장률 코스피200 상위 42% → 59점","inputs":[{"label":"매출액(2025.12)","value":"49,636억원"},{"label":"컨센서스(2026.12)","value":"56,250억원"},{"label":"전망 성장률","value":"+13.3%"}],"reasons":[]},"opGrowth":{"score":47,"label":"영업이익 성장 전망","explain":"애널리스트들이 전망하는 2026.12 영업이익이 최근 확정 실적 대비 얼마나 늘어나는지를 봅니다. 2025.12 8,787억원 → 2026.12 컨센서스 10,139억원 (+15.4%). 전망 성장률 코스피200 하위 32% → 47점","inputs":[{"label":"영업이익(2025.12)","value":"8,787억원"},{"label":"컨센서스(2026.12)","value":"10,139억원"},{"label":"전망 성장률","value":"+15.4%"}],"reasons":[]},"epsGrowth":{"score":46,"label":"EPS 성장 전망","explain":"애널리스트들이 전망하는 2026.12 EPS이 최근 확정 실적 대비 얼마나 늘어나는지를 봅니다. 2025.12 8,558원 → 2026.12 컨센서스 10,116원 (+18.2%). 전망 성장률 코스피200 하위 30% → 46점","inputs":[{"label":"EPS(2025.12)","value":"8,558원"},{"label":"컨센서스(2026.12)","value":"10,116원"},{"label":"전망 성장률","value":"+18.2%"}],"reasons":[]},"targetUpside":{"score":81,"label":"목표주가","explain":"애널리스트 평균 목표주가가 현재 주가보다 얼마나 높은지(괴리율)를 봅니다. 평균 목표주가 125,000원 vs 현재가 91,800원 → 괴리율 36.2%. 괴리율 36.2%는 통상적 상방 편향(+15% 내외)을 크게 상회 → 81점 (참고: 투자의견 평균 4/5)","inputs":[{"label":"평균 목표주가","value":"125,000원"},{"label":"현재가","value":"91,800원"},{"label":"괴리율","value":"+36.2%"},{"label":"투자의견 평균","value":"4/5"}],"reasons":["목표주가 괴리율이 상방 편향을 크게 상회"]},"valuation":{"score":64,"label":"밸류에이션","explain":"이익·자산 대비 주가 수준(PER·PBR)이 싼지 비싼지를 절대 구간과 지수 내 상대 위치로 함께 봅니다. 추정PER 9.1배(전망 이익 기준), PBR 1.8배. PER 절대 구간 저평가 · 지수 내 상위 32% → 64점","inputs":[{"label":"추정PER","value":"9.1배"},{"label":"PBR","value":"1.8배"}],"reasons":["PER 9.1배로 지수 하위 32% 저평가"]},"risk":{"score":0,"label":"전망 리스크","explain":"전망 측면의 위험 신호(이익 감소 전망, 목표주가 하회, 성장 없는 고평가)를 누적 가산합니다. 확인된 전망 위험 신호가 없습니다 (0점).","inputs":[],"reasons":[]}},"reasons":["2026.12 컨센서스 영업이익 +15.4% 전망","평균 목표주가 대비 상승여력 36.2%","2026.12 컨센서스 매출액 +13.3% 전망","추정PER 9.1배로 지수 하위 32% 저평가"],"hasConsensus":true},"tech":{"buy":52,"sell":20,"parts":{"rsi":{"score":65,"label":"RSI","explain":"최근 14일 상승/하락 강도로 과매수·과매도를 측정하되, 추세 방향에 따라 해석을 달리합니다. RSI(14) 49.9 / 추세 상태: 상승추세. 중립권 → 65점","inputs":[{"label":"RSI(14)","value":49.9},{"label":"추세 상태","value":"상승추세"}],"reasons":[]},"macd":{"score":22,"label":"MACD","explain":"단기(12일)·장기(26일) 이동평균 차이로 모멘텀의 방향 전환을 포착합니다. MACD 505.77 / 시그널 747.29 / 히스토그램 -241.52 (축소) / 상태: 데드크로스. 데드크로스 + 히스토그램 축소 → 22점","inputs":[{"label":"MACD","value":505.77},{"label":"시그널","value":747.29},{"label":"히스토그램","value":-241.52},{"label":"상태","value":"데드크로스"}],"reasons":["MACD 시그널 하향 이탈(데드크로스)"]},"trend":{"score":61,"label":"추세","explain":"주가가 20일·60일 이동평균 위에 있는지, 최근 20일 상승 폭과 52주 내 위치로 추세 건강도를 봅니다. 종가 91,800 vs MA20 92,535 / MA60 91,003, 20일 모멘텀 +5.5%, 52주 위치 50.4 (0=최저가, 100=최고가). MA20 하회/MA60 상회 · 모멘텀 +5.5%, 52주 중간권 → 61점","inputs":[{"label":"종가","value":"91,800"},{"label":"MA20","value":"92,535"},{"label":"MA60","value":"91,003"},{"label":"20일 모멘텀","value":"+5.5%"},{"label":"52주 위치","value":50.4}],"reasons":["MA20 하회/MA60 상회","52주 중간권"]},"band":{"score":60,"label":"볼린저밴드","explain":"20일 평균 대비 주가가 통계적 밴드(±2σ)의 어디에 있는지로 단기 과열·눌림을 측정합니다. %b 0.44 (0=하단 밴드, 1=상단 밴드), MA20 이격도 -0.8%. %b 밴드 중간 → 60점","inputs":[{"label":"%b(20,2)","value":0.44},{"label":"MA20 이격도","value":"-0.8%"}],"reasons":[]},"volume":{"score":null,"label":"거래량·수급","explain":"거래대금이 최근 20일 평균 대비 통계적으로 얼마나 튀었는지(Z-score)와 투자자별(외국인·기관·개인) 5일 순매수 방향을 봅니다. 거래대금 Z -0.5 (2 이상이면 급증), 외인+기관 5일 순매수/거래량 11.53% (개인 -9.44%). 외인+기관 순매수 우위 → 추세 파트에 +3점 반영","inputs":[{"label":"거래대금 Z(20)","value":-0.5},{"label":"외국인 5일 순매수/거래량","value":"9.23%"},{"label":"기관 5일 순매수/거래량","value":"2.29%"},{"label":"개인 5일 순매수/거래량","value":"-9.44%"},{"label":"외인+기관 5일 순매수/거래량","value":"11.53%"}],"reasons":[],"buyScore":3,"sellScore":0},"sellSignals":{"score":20,"label":"매도 신호","explain":"과열·추세이탈·투매 등 \"지금 팔 이유\"가 되는 이벤트를 하나씩 가산합니다(기본 15점). 발동 신호: 데드크로스(+15), 건전한 추세 진행(감산)(-10). 매도 신호 1건 → TECH_sell 20점","inputs":[{"label":"데드크로스","value":"+15점"},{"label":"건전한 추세 진행(감산)","value":"-10점"}],"reasons":["데드크로스(+15)","건전한 추세 진행(감산)(-10)"],"sellScore":20}},"reasons":["MACD 시그널 하향 이탈(데드크로스)","RSI 49.9 중립권","20일 모멘텀 +5.5%"]}},"indicators":{"rsi":49.9,"macd":505.77,"signal":747.29,"hist":-241.52,"ma20":92535,"ma60":91003.3,"momentum20d":5.5,"bollingerB":0.44,"pos52w":50.4,"volumeZ":-0.5,"disparity20":-0.8,"atrPct":5.4,"flowRatio":0.1153,"flow":{"foreign5":73684,"organ5":18310,"indiv5":-75298,"foreignRatio":0.0923,"organRatio":0.0229,"indivRatio":-0.0944},"foreignRate":54.82,"trendState":"up"},"targetPrice":null,"verdict":{"stance":"중립","text":"코스피200 상대평가 실버 등급으로 매수 매력도(BUY) 60점, 매도 신호(SELL) 11점입니다. 가장 강한 항목은 수익성(85점)이고, 상대적 약점은 MACD(22점)입니다. 기술적으로는 상승추세 국면에 RSI 49.9(중립권)입니다."},"financials":{"years":["2023.12","2024.12","2025.12","2026.12(E)"],"revenue":[39665,43101,49636,56250],"op":[7313,7954,8787,10139],"netIncome":[4710,5655,6175,7013],"roe":[19.03,19.38,18.14,18.51],"debtRatio":[83.91,80.27,93.71,null],"per":[8.96,8.73,10.15,8.97],"pbr":[1.57,1.5,1.7,1.54],"eps":[6386,7664,8558,10116]},"chart":{"dates":["2026-01-27","2026-01-28","2026-01-29","2026-01-30","2026-02-02","2026-02-03","2026-02-04","2026-02-05","2026-02-06","2026-02-09","2026-02-10","2026-02-11","2026-02-12","2026-02-13","2026-02-19","2026-02-20","2026-02-23","2026-02-24","2026-02-25","2026-02-26","2026-02-27","2026-03-03","2026-03-04","2026-03-05","2026-03-06","2026-03-09","2026-03-10","2026-03-11","2026-03-12","2026-03-13","2026-03-16","2026-03-17","2026-03-18","2026-03-19","2026-03-20","2026-03-23","2026-03-24","2026-03-25","2026-03-26","2026-03-27","2026-03-30","2026-03-31","2026-04-01","2026-04-02","2026-04-03","2026-04-06","2026-04-07","2026-04-08","2026-04-09","2026-04-10","2026-04-13","2026-04-14","2026-04-15","2026-04-16","2026-04-17","2026-04-20","2026-04-21","2026-04-22","2026-04-23","2026-04-24","2026-04-27","2026-04-28","2026-04-29","2026-04-30","2026-05-04","2026-05-06","2026-05-07","2026-05-08","2026-05-11","2026-05-12","2026-05-13","2026-05-14","2026-05-15","2026-05-18","2026-05-19","2026-05-20","2026-05-21","2026-05-22","2026-05-26","2026-05-27","2026-05-28","2026-05-29","2026-06-01","2026-06-02","2026-06-04","2026-06-05","2026-06-08","2026-06-09","2026-06-10","2026-06-11","2026-06-12","2026-06-15","2026-06-16","2026-06-17","2026-06-18","2026-06-19","2026-06-22","2026-06-23","2026-06-24","2026-06-25","2026-06-26","2026-06-29","2026-06-30","2026-07-01","2026-07-02","2026-07-03","2026-07-06","2026-07-07","2026-07-08","2026-07-09","2026-07-10","2026-07-13","2026-07-14","2026-07-15","2026-07-16","2026-07-20","2026-07-21","2026-07-22","2026-07-23","2026-07-24"],"close":[75900,79600,81600,83400,83600,84700,86100,83700,78200,82600,87300,86200,87900,89600,88400,87300,86600,85100,83800,84100,81900,81400,73800,74500,75200,72200,72300,74100,74200,73600,73900,74800,75000,73000,74400,70900,72300,74100,73300,73500,72500,72200,71800,71900,72000,72400,77800,78200,74700,75500,79900,81400,82100,83300,83300,83100,81400,80800,79600,85900,86100,85500,87400,86100,86700,83200,86900,87600,92800,91800,94600,96200,94700,92500,91100,88200,93700,94200,93700,91500,92400,90000,90000,94600,93000,94200,87400,92400,92000,92000,89000,91300,91200,91800,91000,87400,86000,86000,86300,87000,85700,91300,90300,95000,96100,95400,95000,96800,91700,85000,89900,91700,94200,95700,96700,92400,93500,91800,90700,91800],"volume":[278920,410340,426790,521850,483854,550496,355822,310173,617528,418593,467185,385207,599680,562331,261326,583207,696055,843135,780453,786842,7067695,382449,716752,599640,291417,318961,342977,227134,404848,224380,189948,168710,143759,188595,411340,235735,193707,132748,173669,220156,196815,420265,302293,392096,114054,94171,598258,255400,329711,147623,400651,231692,261434,180698,423536,122920,645573,274247,662931,692190,559551,184991,282711,384403,162916,599845,277014,318992,455997,373454,427277,305818,579237,246050,310244,292672,308033,323450,369422,189586,246327,338505,197829,350751,261608,389470,462152,229286,361717,586697,228148,227541,235715,151592,177300,484791,132405,192243,191574,172744,303280,162732,266857,216004,203239,202258,143598,142388,187490,299296,166662,155203,486271,169242,320127,142960,120285,96942,117733,161975],"rsi14":[30,46.5,52.9,57.9,58.4,61.2,64.5,55.7,41.7,52.1,60.2,57.8,60.5,63,60.1,57.4,55.7,52.2,49.3,50,45.1,44,31.9,33.7,35.5,31.5,31.8,36.8,37,36,37,39.8,40.4,36.3,40.9,34.2,38.5,43.6,42,42.6,40.3,39.7,38.8,39.1,39.5,41.2,58.1,59.1,48.8,50.9,60.5,63.2,64.4,66.4,66.4,65.7,59.7,57.7,53.9,66.5,66.8,64.9,68.1,63.8,64.9,54.6,61.5,62.7,70,67.3,70.7,72.5,68.3,62.6,59.2,52.8,61.3,62,60.9,56,57.5,52.4,52.4,60.2,56.7,58.7,46.1,53.9,53.2,53.2,48.1,51.9,51.7,52.8,51.2,44.6,42.3,42.3,43,44.8,42.2,54.4,52.3,60.1,61.7,60.1,59.1,62.1,50.8,40.5,48.7,51.4,54.9,56.9,58.2,50.9,52.6,49.8,48,49.9],"macd":[-2857.13,-2491.88,-2017.78,-1479.75,-1025.39,-569.99,-95.01,86.76,-210.57,-90.12,380.2,656.61,1001.29,1395.55,1592.81,1641.46,1605.02,1438.53,1187.99,1002.09,669.52,361.45,-490.3,-1096.21,-1502.58,-2043.16,-2435.43,-2571.42,-2640.68,-2712.72,-2714.31,-2612.83,-2487.6,-2520.67,-2406.18,-2568.26,-2554.29,-2370.65,-2263.58,-2137.94,-2094.91,-2061.26,-2043.31,-1997.98,-1931.73,-1825.89,-1291.4,-826.01,-731.18,-584.73,-112.33,378.72,814.98,1243.21,1564.55,1782.53,1797.39,1740.68,1580.69,1939.89,2215.16,2357.72,2594.11,2646.05,2704.46,2440.19,2500.5,2575.09,3019,3252.61,3621.94,3997.66,4126.81,4005.47,3753.07,3281.22,3312.89,3339.83,3282.99,3025.55,2861.16,2508.31,2203.28,2306.14,2232.8,2245.63,1687.64,1630.1,1534.53,1442.16,1114.05,1027.76,940.46,909.21,810.55,436.83,27.38,-293.73,-518.04,-632.03,-817.84,-507.38,-338.12,173.26,659.7,977.45,1183.35,1474.77,1279.45,577.37,411.61,420.64,622.35,892.95,1174.56,1038.78,1008.32,837.35,606.1,505.77],"signal":[-2754.7,-2702.14,-2565.27,-2348.16,-2083.61,-1780.88,-1443.71,-1137.62,-952.21,-779.79,-547.79,-306.91,-45.27,242.89,512.88,738.59,911.88,1017.21,1051.36,1041.51,967.11,845.98,578.72,243.74,-105.53,-493.05,-881.53,-1219.51,-1503.74,-1745.54,-1939.29,-2074,-2156.72,-2229.51,-2264.84,-2325.53,-2371.28,-2371.15,-2349.64,-2307.3,-2264.82,-2224.11,-2187.95,-2149.96,-2106.31,-2050.23,-1898.46,-1683.97,-1493.41,-1311.67,-1071.81,-781.7,-462.36,-121.25,215.91,529.23,782.86,974.43,1095.68,1264.52,1454.65,1635.26,1827.03,1990.84,2133.56,2194.89,2256.01,2319.82,2459.66,2618.25,2818.99,3054.72,3269.14,3416.41,3483.74,3443.23,3417.16,3401.7,3377.96,3307.47,3218.21,3076.23,2901.64,2782.54,2672.59,2587.2,2407.29,2251.85,2108.39,1975.14,1802.92,1647.89,1506.4,1386.97,1271.68,1104.71,889.25,652.65,418.51,208.4,3.16,-98.95,-146.79,-82.78,65.72,248.06,435.12,643.05,770.33,731.74,667.71,618.3,619.11,673.88,774.01,826.97,863.24,858.06,807.67,747.29]}}