{"code":"285130","name":"SK케미칼","updatedAt":"2026-07-24T14:50:22+09:00","price":41100,"change":300,"changeRate":0.74,"buy":58,"sell":16,"grade":"silver","scores":{"fin":{"total":47,"parts":{"profitability":{"score":22,"label":"수익성","explain":"자본과 매출을 이익으로 바꾸는 효율을 ROE와 영업이익률로 측정합니다. 2025.12 확정 기준 ROE 2%, 영업이익률 0%. ROE 코스피200 하위 22% · 영업이익률 하위 9% → 수익성 22점","inputs":[{"label":"ROE(2025.12)","value":"2%"},{"label":"영업이익률","value":"0%"}],"reasons":["ROE 코스피200 하위 22%","영업이익률 하위 9%"]},"growth":{"score":65,"label":"성장성","explain":"매출과 영업이익이 얼마나 빠르게 늘고 있는지를 최근 1년과 2년 추세로 함께 봅니다. 2025.12 매출 YoY +36.2%, 2년 연평균 매출 +16.3%. 영업이익 성장 코스피200 상위 15% 수준 → 성장성 65점","inputs":[{"label":"매출 YoY","value":"+36.2%"},{"label":"영업이익 YoY","value":"+99.6%"},{"label":"2년 매출 CAGR","value":"+16.3%"}],"reasons":[]},"stability":{"score":62,"label":"안정성","explain":"부채 부담과 배당 여력으로 재무 하방 안정성을 측정합니다. 부채비율 93.9% (2025.12), 배당수익률 2.8%. 부채비율 안정적 · 배당 상위 38% → 안정성 62점","inputs":[{"label":"부채비율(2025.12)","value":"93.9%"},{"label":"배당수익률","value":"2.8%"}],"reasons":["부채비율 93.9%로 안정적"]},"risk":{"score":15,"label":"재무 리스크","explain":"재무제표에서 확인되는 위험 신호(적자, 과다 부채, 매출 급감)를 누적 가산합니다. 발동 신호: 영업이익 적자(+15). 위험 신호 1건 → 재무 리스크 15점 (신호 없음 = 0점이 기본)","inputs":[{"label":"영업이익 적자","value":"+15점"}],"reasons":["영업이익 적자(+15)"]}},"reasons":["ROE 2%로 코스피200 하위 22%","2025.12 영업이익 적자 지속(적자폭 축소)","부채비율 93.9%로 재무구조 안정적"]},"out":{"total":73,"parts":{"revenueGrowth":{"score":68,"label":"매출 성장 전망","explain":"애널리스트들이 전망하는 2026.12 매출액이 최근 확정 실적 대비 얼마나 늘어나는지를 봅니다. 2025.12 23,652억원 → 2026.12 컨센서스 28,038억원 (+18.5%). 전망 성장률 코스피200 상위 28% → 68점","inputs":[{"label":"매출액(2025.12)","value":"23,652억원"},{"label":"컨센서스(2026.12)","value":"28,038억원"},{"label":"전망 성장률","value":"+18.5%"}],"reasons":[]},"opGrowth":{"score":70,"label":"영업이익 성장 전망","explain":"애널리스트들이 전망하는 2026.12 영업이익이 최근 확정 실적 대비 얼마나 늘어나는지를 봅니다. 2025.12 -2억원 → 2026.12 적자 → 흑자전환 전망. 흑자전환 전망으로 70점 부여 (직전 이익 기저가 낮아 기저효과 반영, 점수 상한 적용)","inputs":[{"label":"영업이익(2025.12)","value":"-2억원"},{"label":"컨센서스(2026.12)","value":"79억원"},{"label":"전망 성장률","value":"흑자전환"}],"reasons":["2026.12 영업이익 흑자전환 전망"]},"epsGrowth":{"score":91,"label":"EPS 성장 전망","explain":"애널리스트들이 전망하는 2026.12 EPS이 최근 확정 실적 대비 얼마나 늘어나는지를 봅니다. 2025.12 2,304원 → 2026.12 컨센서스 7,719원 (+235%). 전망 성장률 코스피200 상위 13% → 91점","inputs":[{"label":"EPS(2025.12)","value":"2,304원"},{"label":"컨센서스(2026.12)","value":"7,719원"},{"label":"전망 성장률","value":"+235%"}],"reasons":[]},"targetUpside":{"score":95,"label":"목표주가","explain":"애널리스트 평균 목표주가가 현재 주가보다 얼마나 높은지(괴리율)를 봅니다. 평균 목표주가 80,000원 vs 현재가 41,100원 → 괴리율 80%. 괴리율 80%는 통상적 상방 편향(+15% 내외)을 크게 상회 → 95점 (참고: 투자의견 평균 4/5)","inputs":[{"label":"평균 목표주가","value":"80,000원"},{"label":"현재가","value":"41,100원"},{"label":"괴리율","value":"+80%"},{"label":"투자의견 평균","value":"4/5"}],"reasons":["목표주가 괴리율이 상방 편향을 크게 상회"]},"valuation":{"score":36,"label":"밸류에이션","explain":"이익·자산 대비 주가 수준(PER·PBR)이 싼지 비싼지를 절대 구간과 지수 내 상대 위치로 함께 봅니다. PER 63.6배, PBR 0.4배. PER 절대 구간 고평가 · 지수 내 하위 6% → 36점","inputs":[{"label":"PER","value":"63.6배"},{"label":"PBR","value":"0.4배"}],"reasons":["PER 63.6배로 지수 상위 6% 고평가 부담"]},"risk":{"score":0,"label":"전망 리스크","explain":"전망 측면의 위험 신호(이익 감소 전망, 목표주가 하회, 성장 없는 고평가)를 누적 가산합니다. 확인된 전망 위험 신호가 없습니다 (0점).","inputs":[],"reasons":[]}},"reasons":["2026.12 컨센서스 영업이익 흑자전환 전망","평균 목표주가 대비 상승여력 80%","2026.12 컨센서스 매출액 +18.5% 전망","PER 63.6배로 지수 상위 6% 고평가 부담"],"hasConsensus":true},"tech":{"buy":56,"sell":23,"parts":{"rsi":{"score":45,"label":"RSI","explain":"최근 14일 상승/하락 강도로 과매수·과매도를 측정하되, 추세 방향에 따라 해석을 달리합니다. RSI(14) 50.9 / 추세 상태: 하락추세. 중립권 → 45점","inputs":[{"label":"RSI(14)","value":50.9},{"label":"추세 상태","value":"하락추세"}],"reasons":[]},"macd":{"score":82,"label":"MACD","explain":"단기(12일)·장기(26일) 이동평균 차이로 모멘텀의 방향 전환을 포착합니다. MACD -1032.92 / 시그널 -1269.92 / 히스토그램 237 (확대) / 상태: 골든크로스. 골든크로스 + 히스토그램 확대 → 82점","inputs":[{"label":"MACD","value":-1032.92},{"label":"시그널","value":-1269.92},{"label":"히스토그램","value":237},{"label":"상태","value":"골든크로스"}],"reasons":["MACD 시그널 상향 돌파(골든크로스)"]},"trend":{"score":49,"label":"추세","explain":"주가가 20일·60일 이동평균 위에 있는지, 최근 20일 상승 폭과 52주 내 위치로 추세 건강도를 봅니다. 종가 41,100 vs MA20 40,088 / MA60 44,752, 20일 모멘텀 +4.8%, 52주 위치 10 (0=최저가, 100=최고가). MA20 상회/MA60 하회 · 모멘텀 +4.8%, 52주 바닥권(추세 훼손) → 49점","inputs":[{"label":"종가","value":"41,100"},{"label":"MA20","value":"40,088"},{"label":"MA60","value":"44,752"},{"label":"20일 모멘텀","value":"+4.8%"},{"label":"52주 위치","value":10}],"reasons":["MA20 상회/MA60 하회","52주 바닥권(추세 훼손)"]},"band":{"score":48,"label":"볼린저밴드","explain":"20일 평균 대비 주가가 통계적 밴드(±2σ)의 어디에 있는지로 단기 과열·눌림을 측정합니다. %b 0.65 (0=하단 밴드, 1=상단 밴드), MA20 이격도 +2.5%. %b 밴드 중간 → 48점","inputs":[{"label":"%b(20,2)","value":0.65},{"label":"MA20 이격도","value":"+2.5%"}],"reasons":[]},"volume":{"score":null,"label":"거래량·수급","explain":"거래대금이 최근 20일 평균 대비 통계적으로 얼마나 튀었는지(Z-score)와 외국인·기관 5일 순매수 방향을 봅니다. 거래대금 Z 0.5 (2 이상이면 급증), 외인+기관 5일 순매수/거래량 7.14%. 외인+기관 순매수 우위 → 추세 파트에 +3점 반영","inputs":[{"label":"거래대금 Z(20)","value":0.5},{"label":"외인+기관 5일 순매수/거래량","value":"7.14%"}],"reasons":[],"buyScore":3,"sellScore":0},"sellSignals":{"score":23,"label":"매도 신호","explain":"과열·추세이탈·투매 등 \"지금 팔 이유\"가 되는 이벤트를 하나씩 가산합니다(기본 15점). 발동 신호: MA20 < MA60 역배열(+8). 매도 신호 1건 → TECH_sell 23점","inputs":[{"label":"MA20 < MA60 역배열","value":"+8점"}],"reasons":["MA20 < MA60 역배열(+8)"],"sellScore":23}},"reasons":["MACD 시그널 상향 돌파(골든크로스)","RSI 50.9 중립권","20일 모멘텀 +4.8%"]}},"indicators":{"rsi":50.9,"macd":-1032.92,"signal":-1269.92,"hist":237,"ma20":40087.5,"ma60":44751.7,"momentum20d":4.8,"bollingerB":0.65,"pos52w":10,"volumeZ":0.5,"disparity20":2.5,"atrPct":5.4,"flowRatio":0.0714,"foreignRate":11.12,"trendState":"down"},"targetPrice":null,"verdict":{"stance":"중립","text":"코스피200 상대평가 실버 등급으로 매수 매력도(BUY) 58점, 매도 신호(SELL) 16점입니다. 가장 강한 항목은 목표주가 괴리율(95점)이고, 최대 리스크는 영업이익 적자 등 위험 신호 1건입니다. 기술적으로는 하락추세 국면에 RSI 50.9(중립권)입니다."},"financials":{"years":["2023.12","2024.12","2025.12","2026.12(E)"],"revenue":[17488,17368,23652,28038],"op":[833,-452,-2,79],"netIncome":[478,-44,273,1329],"roe":[1.87,0.41,2,6.45],"debtRatio":[55.42,76.96,93.85,null],"per":[32.7,97.08,28.43,5.29],"pbr":[0.61,0.39,0.56,0.33],"eps":[2058,456,2304,7719]},"chart":{"dates":["2026-01-27","2026-01-28","2026-01-29","2026-01-30","2026-02-02","2026-02-03","2026-02-04","2026-02-05","2026-02-06","2026-02-09","2026-02-10","2026-02-11","2026-02-12","2026-02-13","2026-02-19","2026-02-20","2026-02-23","2026-02-24","2026-02-25","2026-02-26","2026-02-27","2026-03-03","2026-03-04","2026-03-05","2026-03-06","2026-03-09","2026-03-10","2026-03-11","2026-03-12","2026-03-13","2026-03-16","2026-03-17","2026-03-18","2026-03-19","2026-03-20","2026-03-23","2026-03-24","2026-03-25","2026-03-26","2026-03-27","2026-03-30","2026-03-31","2026-04-01","2026-04-02","2026-04-03","2026-04-06","2026-04-07","2026-04-08","2026-04-09","2026-04-10","2026-04-13","2026-04-14","2026-04-15","2026-04-16","2026-04-17","2026-04-20","2026-04-21","2026-04-22","2026-04-23","2026-04-24","2026-04-27","2026-04-28","2026-04-29","2026-04-30","2026-05-04","2026-05-06","2026-05-07","2026-05-08","2026-05-11","2026-05-12","2026-05-13","2026-05-14","2026-05-15","2026-05-18","2026-05-19","2026-05-20","2026-05-21","2026-05-22","2026-05-26","2026-05-27","2026-05-28","2026-05-29","2026-06-01","2026-06-02","2026-06-04","2026-06-05","2026-06-08","2026-06-09","2026-06-10","2026-06-11","2026-06-12","2026-06-15","2026-06-16","2026-06-17","2026-06-18","2026-06-19","2026-06-22","2026-06-23","2026-06-24","2026-06-25","2026-06-26","2026-06-29","2026-06-30","2026-07-01","2026-07-02","2026-07-03","2026-07-06","2026-07-07","2026-07-08","2026-07-09","2026-07-10","2026-07-13","2026-07-14","2026-07-15","2026-07-16","2026-07-20","2026-07-21","2026-07-22","2026-07-23","2026-07-24"],"close":[68200,68900,68400,67200,64200,65900,68000,65400,64800,65500,65900,64300,64000,63000,64300,64400,64100,64700,68300,68300,68800,64400,54800,59400,59200,55200,56900,60000,58900,57400,56300,57800,59500,57100,58600,55100,55500,56200,54300,55000,52800,52600,54400,51100,51300,51600,51400,54300,55500,57000,57200,56900,57700,59600,59300,57800,57800,58200,58400,58700,57700,57700,62400,59400,59700,58200,56400,55400,53100,50500,49500,51500,48700,46950,45450,43300,44050,46300,46250,43800,43550,43150,41550,41850,42000,41450,38750,40500,40750,44550,44050,45850,46700,45750,44400,44050,40700,38850,39400,39200,37300,40600,39450,40950,41350,41900,42700,42950,40600,40800,40700,39850,39600,39400,39250,37650,37200,37600,40800,41100],"volume":[48124,79578,87881,126052,84384,64048,63812,50952,46469,73718,47018,101908,81645,75951,51645,49178,30978,43366,137058,110138,105198,108517,145484,52430,36369,43341,28899,43103,42657,26718,28992,23370,40891,37299,39733,65569,46734,56162,45828,50215,61757,36751,43656,50739,26558,28795,35288,57121,68456,38185,46203,35952,52442,80186,53529,49150,30093,30829,63561,43628,51808,78155,142229,105425,40933,82885,90296,45807,82722,126099,88768,95110,126055,63808,104609,103066,79802,113845,66682,92203,84759,91152,113513,64363,59937,54452,64582,68534,63638,173663,76772,85979,95377,63949,80558,75801,80565,97517,73783,49893,73909,75448,73437,70685,53577,82142,51956,53099,60604,72974,33261,41359,61537,39229,30123,28779,51525,29968,75470,62299],"rsi14":[50.2,52.9,50.8,46,36.8,43.7,50.8,43.5,42,44.4,45.8,41.3,40.5,37.9,43.1,43.4,42.5,45.1,57.3,57.3,58.8,44.3,28,39.5,39.2,33.8,37.7,44.2,42.5,40.2,38.6,42.1,45.8,41.7,45,39.4,40.3,42,38.8,40.6,37,36.7,41.6,36.1,36.6,37.5,37.1,45.4,48.4,52,52.4,51.6,53.7,58.3,57.3,52.6,52.6,53.8,54.4,55.3,51.5,51.5,64.8,54.5,55.3,50.7,45.8,43.3,38.1,33.3,31.6,38.3,33.4,30.7,28.6,25.9,28.5,35.6,35.6,31.6,31.2,30.5,28.1,29.2,29.8,28.8,24.6,31.6,32.6,45.3,44.2,49.3,51.5,48.9,45.4,44.5,36.9,33.6,35.5,35.1,31.5,42.4,40,44.4,45.6,47.2,49.5,50.3,43.8,44.4,44.1,41.7,41,40.4,40,35.3,34.1,36.2,49.9,50.9],"macd":[-390.2,-268.5,-209.98,-257.47,-531.05,-603.73,-486.28,-596.12,-723.25,-758.76,-746.04,-855.2,-954.91,-1101.92,-1100.84,-1079.47,-1074.36,-1010.25,-661.32,-380.41,-116.11,-258.7,-1133.29,-1438.64,-1677.43,-2164.49,-2385.81,-2284.73,-2267.25,-2347.37,-2471.14,-2420.3,-2217.27,-2224.38,-2084.95,-2231.15,-2288.36,-2251.26,-2348.11,-2341.39,-2484.94,-2585.04,-2490.42,-2651.16,-2730.92,-2738.36,-2728.94,-2459.12,-2123.97,-1717.52,-1363.56,-1094.63,-807.63,-422.01,-139.01,-35.35,46.26,141.58,230.6,321.66,309.56,296.55,657.91,694.21,738.67,645.43,421.43,161.36,-227.72,-737.36,-1208.02,-1403.46,-1763.95,-2165.89,-2575.77,-3039.06,-3307.57,-3300.77,-3261.81,-3389.55,-3470.96,-3527.09,-3658.5,-3695.84,-3671.01,-3653.6,-3813.7,-3756.08,-3648.18,-3218.94,-2885.84,-2448.39,-2009.95,-1719.33,-1579.72,-1480.27,-1652.71,-1916.56,-2057.57,-2160.55,-2368.17,-2240.61,-2206.87,-2035.63,-1846.36,-1633.15,-1383.68,-1152.52,-1145.74,-1111.41,-1079.83,-1110.59,-1141.97,-1169.5,-1189.71,-1319.62,-1442.26,-1490,-1255.15,-1032.92],"signal":[-547.8,-491.94,-435.55,-399.93,-426.16,-461.67,-466.59,-492.5,-538.65,-582.67,-615.34,-663.31,-721.63,-797.69,-858.32,-902.55,-936.91,-951.58,-893.53,-790.91,-655.95,-576.5,-687.86,-838.01,-1005.9,-1237.62,-1467.25,-1630.75,-1758.05,-1875.91,-1994.96,-2080.03,-2107.48,-2130.86,-2121.68,-2143.57,-2172.53,-2188.28,-2220.24,-2244.47,-2292.56,-2351.06,-2378.93,-2433.38,-2492.89,-2541.98,-2579.37,-2555.32,-2469.05,-2318.75,-2127.71,-1921.09,-1698.4,-1443.12,-1182.3,-952.91,-753.08,-574.15,-413.2,-266.22,-151.07,-61.55,82.34,204.72,311.51,378.29,386.92,341.81,227.9,34.85,-213.72,-451.67,-714.13,-1004.48,-1318.74,-1662.8,-1991.76,-2253.56,-2455.21,-2642.08,-2807.85,-2951.7,-3093.06,-3213.62,-3305.1,-3374.8,-3462.58,-3521.28,-3546.66,-3481.12,-3362.06,-3179.33,-2945.45,-2700.23,-2476.13,-2276.95,-2152.11,-2105,-2095.51,-2108.52,-2160.45,-2176.48,-2182.56,-2153.17,-2091.81,-2000.08,-1876.8,-1731.94,-1614.7,-1514.04,-1427.2,-1363.88,-1319.5,-1289.5,-1269.54,-1279.56,-1312.1,-1347.68,-1329.17,-1269.92]}}